{
    "1001": "server error",
    "1002": "方法不存在",
    "1003": "参数错误",
    "1004": "token验证失败",
    "1005": "权限不足",
    "1006": "签名错误",
    "1007": "用户名已存在",
    "1008": "两次密码不相同",
    "1009": "密码长度应在6至24个字符之间，至少1个大写字母，1个小写字母和1个数字",
    "1010": "失败请重试",
    "1011": "用户名或密码错误",
    "1012": "用户名长度应在5至20之间",
    "1013": "注册码不存在",
    "1014": "注册码不归属于你，请检查传入id",
    "1015": "注册码已被使用",
    "1016": "注册码已过期",
    "1017": "权限不够，无法为该用户设置为{roleName}",
    "1020": "access_key或secret_key不正确",
    "1021": "无该条记录",
    "9999": "未知错误"
}